omni_photo_lib/__init__.py
omni_photo_lib/celery_config.py
omni_photo_lib/cloudinary_config.py
omni_photo_lib/generate_task.py
omni_photo_lib/replicatecode.py
omni_photo_lib/utils.py
omni_photo_lib-0.1.44.dist-info/METADATA
omni_photo_lib-0.1.44.dist-info/WHEEL
omni_photo_lib-0.1.44.dist-info/top_level.txt
omni_photo_lib-0.1.44.dist-info/RECORD
