Metadata-Version: 2.1
Name: omni-photo-lib
Version: 0.1.44
Summary: A library for generating images
Home-page: 
Author: Adhithyan
Author-email: adhithyan@omnineura.ai
License: MIT
Classifier: Programming Language :: Python :: 3
Classifier: License :: OSI Approved :: MIT License
Classifier: Operating System :: OS Independent
Requires-Python: >=3.9
Requires-Dist: Pillow
Requires-Dist: requests
Requires-Dist: together
Requires-Dist: celery
